Parameter.v

`ifndef PARAMETER_H_
`define PARAMETER_H_

// Parameter file
`define col 8 // 8 bits data memory.
`define col_memory 16 // 16 bits instruction memory.
`define row_i 15 // instruction memory, instructions number, this number can be changed. Adding more instructions to verify your design is a good idea.
`define row_d 8 // The number of data registers in data memory.
//We only use 8 data. Do not change this number.
// Please only change the value of each data inside test.data file. Total number is fixed at 8.
`define filename "./test/ALU/cmp.o"
`define simulation_time #300
`define data_file "./test/ALU/data_ALU.txt"
`define program_file "./test/ALU/ALU_cmp_prog.txt"
`define pc_length 8 //length of program counter
`endif

DMEM.v
`timescale 1ns / 1ps

/*
Description:
This needs to be a sequential / clocked unit.
At any given cycle, you are either reading from it
or writing to it, with the address given by the address bus.
In case of a lw (load-word) or sw (store-word) instruction,
the address is either immediate or the output of the ALU.
The data output of the DMEM will always go into the register file,
where it gets stored into a register selected by rd.
*/

`include "Parameter.v"

module Data_Memory(
 input clk,
 // address input, shared by read and write port
 input [7:0]   mem_access_addr,

 // write port
 input [7:0]   mem_write_data,
 input     mem_write_en,
 input mem_read,
 // read port
 output [7:0]   mem_read_data
);

reg [`col - 1:0] memory [`row_d - 1:0];   //registers
integer f;
wire [2:0] ram_addr=mem_access_addr[2:0];

initial
 begin
  $readmemb(`data_file, memory);

  f = $fopen(`filename);

  `simulation_time;
  $fclose(f);
 end

 always @(posedge clk) begin
  $fmonitor(f, "time = %d\n", $time,
  "\tmemory[0] = %b\n", memory[0],
  "\tmemory[1] = %b\n", memory[1],
  "\tmemory[2] = %b\n", memory[2],
  "\tmemory[3] = %b\n", memory[3],
  "\tmemory[4] = %b\n", memory[4],
  "\tmemory[5] = %b\n", memory[5],
  "\tmemory[6] = %b\n", memory[6],
  "\tmemory[7] = %b\n", memory[7]);
end

always @(posedge clk) begin
  if (mem_write_en)
   memory[ram_addr] <= mem_write_data;
end
assign mem_read_data = (mem_read==1'b1) ? memory[ram_addr]: 8'd0;

endmodule

ALU.v
//ALU

module ALU (
  input  [7:0] a,  //src1
   input  [7:0] b,  //src2
   input  [2:0] alu_control, //function sel

   output reg [7:0] result,  //result
   output zero);

// a and b are 8 bit values stored in registers
always @(*)
begin
 case(alu_control)
 3'b000: result = a + b; // add
 3'b001: result = a - b; // sub
 3'b010: result = ~a;
 3'b011: result = a<<b;
 3'b100: result = a>>b;
 3'b101: result = a & b; // and
 3'b110: result = a | b; // or
 3'b111: begin if (a<b) result = 16'd1;
    else result = 16'd0;
    end
 default:result = a + b; // add
 endcase
end
assign zero = (result==16'd0) ? 1'b1: 1'b0;

endmodule

Register.v
`timescale 1ns / 1ps

`include "Parameter.v"

/*
Description:

GPRs module.
This is a set of 8 registers, each storing an 8 bit value.
There are 2 output values ra and rb,
whose values are selected based on the instruction word,
as in the instruction definitions given above.
There is one port by which data can be written into one of the registers,
but make sure to give an enable signal to control whether or not to update the value.
*/


module GPRs( //general purpose register
 input    clk,
 // write port
 input    reg_write_en,
 input  [2:0] reg_write_dest,
 input  [7:0] reg_write_data,
 //read port 1
 input  [2:0] reg_read_addr_1,
 output  [7:0] reg_read_data_1,
 //read port 2
 input  [2:0] reg_read_addr_2,
 output  [7:0] reg_read_data_2
);

 reg [7:0] reg_array [7:0];
 integer i;
 integer f;
 // write port
 //reg [2:0] i;
 initial begin
  for(i=0;i<8;i=i+1)
   reg_array[i] <= 8'd0;
 end

 initial
  begin
   f = $fopen(`filename);
   `simulation_time;
   $fclose(f);
  end

 always @ (posedge clk ) begin
 //output registers
 $monitor(f,"time = %d\n", $time,
 "\treg[0] = %b\n", reg_array[0],
 "\treg[1] = %b\n", reg_array[1],
 "\treg[2] = %b\n", reg_array[2],
 "\treg[3] = %b\n", reg_array[3],
 "\treg[4] = %b\n", reg_array[4],
 "\treg[5] = %b\n", reg_array[5],
 "\treg[6] = %b\n", reg_array[6],
 "\treg[7] = %b\n", reg_array[7]);

   if(reg_write_en) begin
    reg_array[reg_write_dest] <= reg_write_data;
   end
 end


 assign reg_read_data_1 = reg_array[reg_read_addr_1];
 assign reg_read_data_2 = reg_array[reg_read_addr_2];



endmodule

IMEM.v
`timescale 1ns / 1ps

/*
Description:

This can be a combinational unit - it takes just the address bus
(8 bit value) as input,
and gives out a 16-bit value that is the instruction to be decoded.
The address is provided by the Program Counter (PC).
*/

`include "Parameter.v"

module Instruction_Memory(
 input[15:0] pc,
 output[15:0] instruction
);

//for 16 bit processor

 reg [`col_memory - 1:0] instruction_memory [`row_i - 1:0];
 wire [3 : 0] rom_addr = pc[4 : 1];
 initial
 begin
  $readmemb(`program_file, instruction_memory,0,14);
 end
 assign instruction =  instruction_memory[rom_addr];

endmodule

PC.v
module ProgramCounter
(
input [7:0]d_in,
input reset, clk,jump,branch,hold,
input [6:0] branch_immem,
input [6:0] jump_line,
output reg [7:0] d_out
);

`include "Parameter.v"

/*
8 bit register.
 Under normal operations, will always increment by 1 on every clock cycle,
to access the next instruction. In case of a JUMP or BRANCH type of instruction,
 will go to the value specified by the output of the ALU
or the immediate operand in the instruction.

*/

//if hold then only operate

always @(clk) begin
if (hold==1'b0) begin
  if (reset)
  d_out <= 8'b00000000;
  else if (jump)
  d_out<=jump_line*2; //jump_line is 7 bits length
  else if (branch)
  d_out<=d_in + {2'b00,branch_immem}; //immem is max 6 bits long
  else if (d_in== `col_memory)
  d_out<=d_in;        //EOP
  else
  d_out <= d_in + 1;
end

else
d_out<=d_in;
end
endmodule

CU.v
`timescale 1ns / 1ps

/*
Controls entire data flow.
See READ_ME for details.
Harvard Architecture.
*/

`include "Parameter.v"
`include "DMEM.v"
`include "ALU.v"
`include "IMEM.v"
`include "Register.v"
`include "PC.v"

module CU(
 input clk,
 input reset,
 output[15:0] pc_out,
 output [7:0] alu_result,
 output reg [2:0] state,
 output reg hold,
 output [3:0] opcode);

//for PC
reg [7:0] pc_current;
wire [7:0] pc_next;
reg [6:0] branch_immem;
reg [6:0] jump_line;
reg jump,branch,mem_write,alu_src,mem_to_reg,reg_write;
//reg hold;

//for imem
wire [15:0] instruction;

//for GPRu
reg    WR,RA;
reg  [2:0] rd;
reg  [7:0] rd_data;
reg  [2:0] ra;
wire [7:0] ra_data;
reg  [2:0] rb;
wire [7:0] rb_data;

//for ALU
reg [2:0] alu_control;
reg [7:0] a,b;
wire [7:0] result;
wire zero;

//for DMEM
reg [7:0] mem_access_addr;
reg [7:0] mem_write_data;
reg mem_write_en;
reg mem_read;
wire [7:0] mem_read_data;

//for CU
//reg [3:0] opcode;
//reg [2:0] state;
reg [5:0] imm;

ProgramCounter PC(pc_current,reset, clk,jump,branch,hold,branch_immem,jump_line,pc_next);

Instruction_Memory IM(.pc(pc_current),.instruction(instruction));

GPRs REG(clk,WR, RA,rd,rd_data,ra,ra_data,rb,rb_data);

ALU alu_unit(a,b,alu_control,result,zero);

Data_Memory DM(clk,mem_access_addr,mem_write_data,mem_write_en,mem_read,mem_read_data);

assign opcode = instruction[15:12];

initial begin
pc_current=0;
hold=0;
state=0;
end

always @(posedge clk)
begin


case(opcode)
4'b0000: begin      //ALU direct data processing
  //hold=1;
  rd=instruction[11:9];
  ra=instruction[8:6];
  rb=instruction[5:3];
  alu_control=instruction[2:0];
  {jump,branch,mem_write,alu_src,mem_to_reg,reg_write}=6'b000001;

  case(state)
  3'b000: begin      //read ra, rb from Instructions
    hold=1;
    RA=1;
    state=state+1;
  end
  3'b001: begin      //allow ALU to process
    RA=0;
    a=ra_data;
    b=rb_data;
    state=state+1;
  end
  3'b010: begin      //allow ALU to process
    rd_data=result;
    state=state+1;
    WR=1;
  end
  3'b011: begin        //write to register
    state=state+1;
    hold=0;
  end
  3'b100: begin
    WR=0;
    state=0;
    hold=1;
  end
  endcase
end

4'b0100:
  begin      //addi rd<=ra+imm
  //hold=1;
  ra=instruction[8:6];
  rd=instruction[5:3];
  imm={instruction[11:9],instruction[2:0]};
  alu_control=0;
  {jump,branch,mem_write,alu_src,mem_to_reg,reg_write}=6'b000001;

  case(state)
  3'b000: begin        //read ra, imem from Instructions
    hold=1;
    RA=1;
    state=state+1;
  end
  3'b001: begin        //process with ALU
    RA=0;
    a=ra_data;
    b={2'b00,imm};
    state=state+1;
  end
  3'b010: begin        //write to register
    rd_data=result;
    state=state+1;
    WR=1;
  end
  3'b011: begin        //write to register

    state=state+1;
    hold=0;
  end
  3'b100:
  begin        //one cycle for latency
    WR=0;
    state=0;
    hold=1;
  end
  endcase
end


4'b1011: begin      //load value.
//  hold=1;
  ra=instruction[8:6];
  rd=instruction[5:3];
  imm={instruction[11:9],instruction[2:0]};
  alu_control=0;
  {jump,branch,mem_write,alu_src,mem_to_reg,reg_write}=6'b000111;

  case(state)
  3'b000: begin        //read ra, imem from Instructions
    hold=1;
    RA=1;
    state=state+1;
  end
  3'b001: begin        //read from memory
    RA=0;
    mem_access_addr=ra_data+{2'b00,imm};
    state=state+1;
  end
  3'b010: begin        //read from memory
    mem_read=1;
    state=state+1;
  end
  3'b011: begin        //write to register rd
    rd_data=mem_read_data;
    mem_read=0;
    state=state+1;
  end
  3'b100: begin        //write to register rd
    WR=1;
    state=state+1;
    hold=0;
  end
  3'b101:
  begin        //one cycle for latency
    WR=0;
    state=0;
    hold=1;
  end
  endcase
end

4'b1111: begin       //store value
  //hold=1;
  ra=instruction[8:6];
  rb=instruction[5:3];
  imm={instruction[11:9],instruction[2:0]};
  alu_control=0;
  {jump,branch,mem_write,alu_src,mem_to_reg,reg_write}=6'b001100;

  case(state)
  3'b000: begin        //read ra,rb imem from Instructions
    hold=1;
    RA=1;
    state=state+1;
  end
  3'b001: begin        //write to data mem
    mem_access_addr=ra_data+{2'b00,imm};
    $display("memory access",mem_access_addr);
    state=state+1;
  end
  3'b010: begin        //latency
    RA=0;
    mem_write_data=rb_data;
    $display("data",rb_data);
    $display("source",rb);
    mem_write_en=1;
    state=state+1;
  end
  3'b011: begin        //latency
    state=state+1;
    hold=0;
  end
  3'b100: begin        //latency
    mem_write_en=0;
    state=0;
    hold=1;
  end
  endcase

end

4'b1000: begin      //branch if equal
  //hold=1;
  ra=instruction[8:6];
  rb=instruction[5:3];
  imm={instruction[11:9],instruction[2:0]};
  alu_control=3'b111;
  {jump,branch,mem_write,alu_src,mem_to_reg,reg_write}=6'b010000;

  case(state)
  3'b000: begin      //read ra, rb from Instructions
    hold=1;
    RA=1;
    state=state+1;
  end
  3'b001: begin      //allow ALU to process
    RA=0;
    a=ra_data;
    b=rb_data;
    state=state+1;
  end
  3'b010: begin        //update pc
    if (zero)
      branch_immem=imm;
    else
      branch=0;
    state=state+1;
    hold=0;
  end
  3'b011: begin     //release all holds
    branch=0;
    state=0;
    hold=1;
  end
endcase

end

4'b0010: begin        //jump
  case(state)
  3'b000: begin
  hold=0;
  {jump,branch,mem_write,alu_src,mem_to_reg,reg_write}=6'b100000;
  jump_line=instruction[6:0];
  state=state+1;
  end
  3'b001: begin
  hold=1;
  jump=0;
  state=0;
  end
  endcase
end

4'b0111: begin
  $display("End Of Program");
  hold=1;
end

endcase

pc_current=pc_next;
end

 assign pc_out = pc_current;
 assign alu_result = result;
endmodule

test_CU_n.v
`timescale 1ns / 1ps

/*
Testbench for RISC module
*/
`include "Parameter.v"
`include "CU.v"

module test_CU;

 // Inputs
 reg clk;
 reg reset;
 wire [15:0] pc_out;
 wire [7:0] alu_result;
 wire [2:0] state;
 wire hold;
 wire [3:0] opcode;
 wire zero;

 // Instantiate the Unit Under Test (UUT)
 CU uut (
  clk,reset,pc_out,alu_result,state,hold,opcode,zero
 );

 initial
  begin
  reset=1;
  $dumpfile("./Waveforms/test_CU_n.vcd");
  $dumpvars(0, clk,reset,pc_out,alu_result,state,hold,opcode,zero);

   clk <=0;
   `simulation_time;
   $finish;
  end

 always
  begin
   #5 clk = ~clk; reset=0;
  end

endmodule

Waveforms/test_CU_n.vcd
$date
	Thu Nov  9 11:06:48 2017
$end
$version
	Icarus Verilog
$end
$timescale
	1ps
$end
$scope module test_CU $end
$var reg 1 ! clk $end
$upscope $end
$scope module test_CU $end
$var reg 1 " reset $end
$upscope $end
$scope module test_CU $end
$var wire 16 # pc_out [15:0] $end
$upscope $end
$scope module test_CU $end
$var wire 8 $ alu_result [7:0] $end
$upscope $end
$scope module test_CU $end
$var wire 3 % state [2:0] $end
$upscope $end
$scope module test_CU $end
$var wire 1 & hold $end
$upscope $end
$scope module test_CU $end
$var wire 4 ' opcode [3:0] $end
$upscope $end
$scope module test_CU $end
$var wire 1 ( zero $end
$upscope $end
$enddefinitions $end
#0
$dumpvars
x(
b1011 '
0&
b0 %
bx $
b0 #
1"
0!
$end
#5000
b1 %
1&
0"
1!
#10000
0!
#15000
b10 %
1!
#20000
0!
#25000
b11 %
1!
#30000
0!
#35000
b100 %
1!
#40000
0!
#45000
0&
b101 %
1!
#50000
0!
#55000
b1 #
1&
b0 %
1!
#60000
0!
#65000
b1 %
1!
#70000
0!
#75000
b10 %
1!
#80000
0!
#85000
b11 %
1!
#90000
0!
#95000
b100 %
1!
#100000
0!
#105000
0&
b101 %
1!
#110000
0!
#115000
b0 '
b10 #
1&
b0 %
1!
#120000
0!
#125000
1(
b0 $
b1 %
1!
#130000
0!
#135000
b10 %
1!
#140000
0!
#145000
b11 %
1!
#150000
0!
#155000
b100 %
1!
#160000
0!
#165000
b101 %
1!
#170000
0!
#175000
b110 %
1!
#180000
0!
#185000
0&
b111 %
1!
#190000
0!
#195000
b1111 '
b11 #
1&
b0 %
1!
#200000
0!
#205000
0(
b111 $
b1 %
1!
#210000
0!
#215000
b10 %
1!
#220000
0!
#225000
b11 %
1!
#230000
0!
#235000
0&
b100 %
1!
#240000
0!
#245000
b111 '
b100 #
1&
b0 %
1!
