Parameter.v
`timescale 1ns / 1ps

`ifndef PARAMETER_H_
`define PARAMETER_H_

// Parameter file
`define col 8 // 8 bits data memory.
`define col_memory 16 // 16 bits instruction memory.
`define row_i 15 // instruction memory, instructions number, this number can be changed. Adding more instructions to verify your design is a good idea.
`define row_d 8 // The number of data registers in data memory.
//We only use 8 data. Do not change this number.
// Please only change the value of each data inside test.data file. Total number is fixed at 8.
`define filename "./demo/1_11_17_16_44.o"
`define simulation_time #300
`define data_file "./demo/data.txt"
`define program_file "./demo/prog.txt"
`endif

CU.v
`timescale 1ns / 1ps


/*
The unit that actually makes the entire processor work as expected.
The input to this is the instruction word,
and the output is a set of control signals
that decide, for example, whether the register file is to updated,
what operation is to be done by the ALU,
whether memory read or write is required etc.
*/

`include "Parameter.v"

module Control_Unit(
      input[3:0] opcode,
      output reg[1:0] alu_op,
      output reg jump,beq,bne,mem_read,mem_write,alu_src,reg_dst,mem_to_reg,reg_write
    );
integer f; //log file

initial begin
f = $fopen(`filename);

  `simulation_time;
  $fclose(f);
end

always @(*)
begin
 $monitor(f,"time = %d\n", $time,"\n Opcode = %d\n",opcode);


 case(opcode)
 4'b0000:  // LW
   begin
    reg_dst = 1'b0;
    alu_src = 1'b1;
    mem_to_reg = 1'b1;
    reg_write = 1'b1;
    mem_read = 1'b1;
    mem_write = 1'b0;
    beq = 1'b0;
    bne = 1'b0;
    alu_op = 2'b10;
    jump = 1'b0;
   end
 4'b0001:  // SW
   begin
    reg_dst = 1'b0;
    alu_src = 1'b1;
    mem_to_reg = 1'b0;
    reg_write = 1'b0;
    mem_read = 1'b0;
    mem_write = 1'b1;
    beq = 1'b0;
    bne = 1'b0;
    alu_op = 2'b10;
    jump = 1'b0;
   end
 4'b0010:  // data_processing
   begin
    reg_dst = 1'b1;
    alu_src = 1'b0;
    mem_to_reg = 1'b0;
    reg_write = 1'b1;
    mem_read = 1'b0;
    mem_write = 1'b0;
    beq = 1'b0;
    bne = 1'b0;
    alu_op = 2'b00;
    jump = 1'b0;
   end
 4'b0011:  // data_processing
   begin
    reg_dst = 1'b1;
    alu_src = 1'b0;
    mem_to_reg = 1'b0;
    reg_write = 1'b1;
    mem_read = 1'b0;
    mem_write = 1'b0;
    beq = 1'b0;
    bne = 1'b0;
    alu_op = 2'b00;
    jump = 1'b0;
   end
 4'b0100:  // data_processing
   begin
    reg_dst = 1'b1;
    alu_src = 1'b0;
    mem_to_reg = 1'b0;
    reg_write = 1'b1;
    mem_read = 1'b0;
    mem_write = 1'b0;
    beq = 1'b0;
    bne = 1'b0;
    alu_op = 2'b00;
    jump = 1'b0;
   end
 4'b0101:  // data_processing
   begin
    reg_dst = 1'b1;
    alu_src = 1'b0;
    mem_to_reg = 1'b0;
    reg_write = 1'b1;
    mem_read = 1'b0;
    mem_write = 1'b0;
    beq = 1'b0;
    bne = 1'b0;
    alu_op = 2'b00;
    jump = 1'b0;
   end
 4'b0110:  // data_processing
   begin
    reg_dst = 1'b1;
    alu_src = 1'b0;
    mem_to_reg = 1'b0;
    reg_write = 1'b1;
    mem_read = 1'b0;
    mem_write = 1'b0;
    beq = 1'b0;
    bne = 1'b0;
    alu_op = 2'b00;
    jump = 1'b0;
   end
 4'b0111:  // data_processing
   begin
    reg_dst = 1'b1;
    alu_src = 1'b0;
    mem_to_reg = 1'b0;
    reg_write = 1'b1;
    mem_read = 1'b0;
    mem_write = 1'b0;
    beq = 1'b0;
    bne = 1'b0;
    alu_op = 2'b00;
    jump = 1'b0;
   end
 4'b1000:  // data_processing
   begin
    reg_dst = 1'b1;
    alu_src = 1'b0;
    mem_to_reg = 1'b0;
    reg_write = 1'b1;
    mem_read = 1'b0;
    mem_write = 1'b0;
    beq = 1'b0;
    bne = 1'b0;
    alu_op = 2'b00;
    jump = 1'b0;
   end
 4'b1001:  // data_processing
   begin
    reg_dst = 1'b1;
    alu_src = 1'b0;
    mem_to_reg = 1'b0;
    reg_write = 1'b1;
    mem_read = 1'b0;
    mem_write = 1'b0;
    beq = 1'b0;
    bne = 1'b0;
    alu_op = 2'b00;
    jump = 1'b0;
   end
 4'b1011:  // BEQ
   begin
    reg_dst = 1'b0;
    alu_src = 1'b0;
    mem_to_reg = 1'b0;
    reg_write = 1'b0;
    mem_read = 1'b0;
    mem_write = 1'b0;
    beq = 1'b1;
    bne = 1'b0;
    alu_op = 2'b01;
    jump = 1'b0;
   end
 4'b1100:  // BNE
   begin
    reg_dst = 1'b0;
    alu_src = 1'b0;
    mem_to_reg = 1'b0;
    reg_write = 1'b0;
    mem_read = 1'b0;
    mem_write = 1'b0;
    beq = 1'b0;
    bne = 1'b1;
    alu_op = 2'b01;
    jump = 1'b0;
   end
 4'b1101:  // J
   begin
    reg_dst = 1'b0;
    alu_src = 1'b0;
    mem_to_reg = 1'b0;
    reg_write = 1'b0;
    mem_read = 1'b0;
    mem_write = 1'b0;
    beq = 1'b0;
    bne = 1'b0;
    alu_op = 2'b00;
    jump = 1'b1;
   end
 default: begin
    reg_dst = 1'b1;
    alu_src = 1'b0;
    mem_to_reg = 1'b0;
    reg_write = 1'b1;
    mem_read = 1'b0;
    mem_write = 1'b0;
    beq = 1'b0;
    bne = 1'b0;
    alu_op = 2'b00;
    jump = 1'b0;
   end
 endcase
 end

endmodule

test_CU.v
`timescale 1ns / 1ps

/*
Testbench for RISC module
*/
`include "Parameter.v"
`include "CU.v"

module test_ALU;

 // Inputs
 reg [3:0] opcode;
 wire [1:0] alu_op;
 wire jump,beq,bne,mem_read,mem_write,alu_src,reg_dst,mem_to_reg,reg_write;


 // Instantiate the Unit Under Test (UUT)
 Control_Unit uut (opcode,alu_op,jump,beq,bne,mem_read,mem_write,
   alu_src,reg_dst,mem_to_reg,reg_write);

 initial
  begin

  $dumpfile("./Waveforms/test_CU.vcd");
  $dumpvars(0, opcode,alu_op,jump,beq,bne,mem_read,mem_write,
    alu_src,reg_dst,mem_to_reg,reg_write);

   opcode=4'd0;

   #20 begin
   opcode=4'd0;
   end

   #30 begin
   opcode=4'd1;
   end

   #40 begin
   opcode=4'd2;
   end

   #50 begin
   opcode=4'd3;
   end

   #60 begin
   opcode=4'd4;
   end

   #70 begin
   opcode=4'd5;
   end

   #80 begin
   opcode=4'd6;
   end

   #90 begin
   opcode=4'd7;
   end

   #100 begin
   opcode=4'd8;
   end

   #110 begin
   opcode=4'd9;
   end

   #120 begin
   opcode=4'd11;
   end

   #130 begin
   opcode=4'd12;
   end

   #140 begin
   opcode=3'd13;
   end

   `simulation_time;
   $finish;
  end

endmodule

Waveforms/test_CU.vcd
$date
	Thu Nov  2 11:58:14 2017
$end
$version
	Icarus Verilog
$end
$timescale
	1ps
$end
$scope module test_ALU $end
$var reg 4 ! opcode [3:0] $end
$upscope $end
$scope module test_ALU $end
$var wire 2 " alu_op [1:0] $end
$upscope $end
$scope module test_ALU $end
$var wire 1 # jump $end
$upscope $end
$scope module test_ALU $end
$var wire 1 $ beq $end
$upscope $end
$scope module test_ALU $end
$var wire 1 % bne $end
$upscope $end
$scope module test_ALU $end
$var wire 1 & mem_read $end
$upscope $end
$scope module test_ALU $end
$var wire 1 ' mem_write $end
$upscope $end
$scope module test_ALU $end
$var wire 1 ( alu_src $end
$upscope $end
$scope module test_ALU $end
$var wire 1 ) reg_dst $end
$upscope $end
$scope module test_ALU $end
$var wire 1 * mem_to_reg $end
$upscope $end
$scope module test_ALU $end
$var wire 1 + reg_write $end
$upscope $end
$enddefinitions $end
#0
$dumpvars
1+
1*
0)
1(
0'
1&
0%
0$
0#
b10 "
b0 !
$end
#50000
1'
0&
0+
0*
b1 !
#90000
b0 "
0'
1+
0(
1)
b10 !
#140000
b11 !
#200000
b100 !
#270000
b101 !
#350000
b110 !
#440000
b111 !
#540000
b1000 !
#650000
b1001 !
#770000
b1 "
1$
0+
0)
b1011 !
#900000
1%
0$
b1100 !
#1040000
b0 "
0%
1+
1)
b101 !
