Parameter.v
`timescale 1ns / 1ps

`ifndef PARAMETER_H_
`define PARAMETER_H_

// Parameter file
`define col 8 // 8 bits data memory.
`define col_memory 16 // 16 bits instruction memory.
`define row_i 15 // instruction memory, instructions number, this number can be changed. Adding more instructions to verify your design is a good idea.
`define row_d 8 // The number of data registers in data memory.
//We only use 8 data. Do not change this number.
// Please only change the value of each data inside test.data file. Total number is fixed at 8.
`define filename "./demo/1_11_17_16_44.o"
`define simulation_time #300
`define data_file "./demo/data.txt"
`define program_file "./demo/prog.txt"
`endif

ALU_control.v
`timescale 1ns / 1ps

/*
Decode the ALU opcode based on the instruction Opcode.
See READ_ME.md for details.
ALU_op and ALU_cnt hold sufficient information to decide which Opcode to use
and whether or not to use the ALU in the first place.
*/

module alu_control( ALU_Cnt, ALUOp, Opcode);
 output reg[2:0] ALU_Cnt;
 input [1:0] ALUOp;
 input [3:0] Opcode;
 wire [5:0] ALUControlIn;
 assign ALUControlIn = {ALUOp,Opcode};
 always @(ALUControlIn)
 casex (ALUControlIn)
   6'b10xxxx: ALU_Cnt=3'b000;
   6'b01xxxx: ALU_Cnt=3'b001;
   6'b000010: ALU_Cnt=3'b000;
   6'b000011: ALU_Cnt=3'b001;
   6'b000100: ALU_Cnt=3'b010;
   6'b000101: ALU_Cnt=3'b011;
   6'b000110: ALU_Cnt=3'b100;
   6'b000111: ALU_Cnt=3'b101;
   6'b001000: ALU_Cnt=3'b110;
   6'b001001: ALU_Cnt=3'b111;
  default: ALU_Cnt=3'b000;
  endcase
endmodule

test_ALU_Control.v
`timescale 1ns / 1ps

/*
Testbench for ALU_Control module
*/
`include "Parameter.v"
`include "ALU_control.v"

module test_ALU_Control;

 // Inputs and Outputs
 wire [2:0] ALU_Cnt;
 reg [1:0] ALUOp;
 reg [3:0] Opcode;

 // Instantiate the Unit Under Test (UUT)
 alu_control uut (ALU_Cnt,ALUOp,Opcode);

 initial
  begin

  $dumpfile("./Waveforms/test_ALU_Control.vcd");
  $dumpvars(0,ALU_Cnt,ALUOp,Opcode);


   #50 begin
   {ALUOp,Opcode}=6'b10xxxx;
   end

   #60 begin
   {ALUOp,Opcode}=6'b01xxxx;
   end

   #70 begin
   {ALUOp,Opcode}=6'b10xxxx;
   end

   #80 begin
   {ALUOp,Opcode}=6'b000010;
   end

   #90 begin
   {ALUOp,Opcode}=6'b000011;
   end

   #100 begin
   {ALUOp,Opcode}=6'b000100;
   end

   #110 begin
   {ALUOp,Opcode}=6'b000101;
   end

   #120 begin
   {ALUOp,Opcode}=6'b000110;
   end

   #130 begin
   {ALUOp,Opcode}=6'b000111;
   end

   #140 begin
   {ALUOp,Opcode}=6'b001000;
   end

   #150 begin
   {ALUOp,Opcode}=6'b001001;
   end

   `simulation_time;
   $finish;
  end

endmodule

Waveforms/test_ALU_Control.vcd
$date
	Thu Nov  2 14:13:28 2017
$end
$version
	Icarus Verilog
$end
$timescale
	1ps
$end
$scope module test_ALU_Control $end
$var wire 3 ! ALU_Cnt [2:0] $end
$upscope $end
$scope module test_ALU_Control $end
$var reg 2 " ALUOp [1:0] $end
$upscope $end
$scope module test_ALU_Control $end
$var reg 4 # Opcode [3:0] $end
$upscope $end
$enddefinitions $end
#0
$dumpvars
bx #
bx "
bx !
$end
#50000
b0 !
b10 "
#110000
b1 !
b1 "
#180000
b0 !
b10 "
#260000
b0 "
b10 #
#350000
b1 !
b11 #
#450000
b10 !
b100 #
#560000
b11 !
b101 #
#680000
b100 !
b110 #
#810000
b101 !
b111 #
#950000
b110 !
b1000 #
#1100000
b111 !
b1001 #
