Parameter.v

`ifndef PARAMETER_H_
`define PARAMETER_H_

// Parameter file
`define col 8 // 8 bits data memory.
`define col_memory 16 // 16 bits instruction memory.
`define row_i 15 // instruction memory, instructions number, this number can be changed. Adding more instructions to verify your design is a good idea.
`define row_d 8 // The number of data registers in data memory.
//We only use 8 data. Do not change this number.
// Please only change the value of each data inside test.data file. Total number is fixed at 8.
`define filename "./demo/1_11_17_16_44.o"
`define simulation_time #300
`define data_file "./demo/data_2.txt"
`define program_file "./demo/assemble/b.txt"
`define pc_length 8 //length of program counter
`endif

DMEM.v
`timescale 1ns / 1ps

/*
Description:
This needs to be a sequential / clocked unit.
At any given cycle, you are either reading from it
or writing to it, with the address given by the address bus.
In case of a lw (load-word) or sw (store-word) instruction,
the address is either immediate or the output of the ALU.
The data output of the DMEM will always go into the register file,
where it gets stored into a register selected by rd.
*/

`include "Parameter.v"

module Data_Memory(
 input clk,
 // address input, shared by read and write port
 input [7:0]   mem_access_addr,

 // write port
 input [7:0]   mem_write_data,
 input     mem_write_en,
 input mem_read,
 // read port
 output reg [7:0]   mem_read_data
);

reg [`col - 1:0] memory [`row_d - 1:0];   //registers
integer f;
wire [2:0] ram_addr=mem_access_addr[2:0];

initial
 begin
  $readmemb(`data_file, memory);

  f = $fopen(`filename);

  `simulation_time;
  $fclose(f);
 end

 always @(posedge clk) begin
  $monitor(f, "time = %d\n", $time,
  "\tmemory[0] = %b\n", memory[0],
  "\tmemory[1] = %b\n", memory[1],
  "\tmemory[2] = %b\n", memory[2],
  "\tmemory[3] = %b\n", memory[3],
  "\tmemory[4] = %b\n", memory[4],
  "\tmemory[5] = %b\n", memory[5],
  "\tmemory[6] = %b\n", memory[6],
  "\tmemory[7] = %b\n", memory[7]);
end

always @(posedge clk) begin
  if (mem_write_en)
   memory[ram_addr] <= mem_write_data;
  else if (mem_read)
  mem_read_data = (mem_read==1'b1) ? memory[ram_addr]: 8'd0;
end


endmodule

ALU.v
//ALU

module ALU (
  input  [7:0] a,  //src1
   input  [7:0] b,  //src2
   input  [2:0] alu_control, //function sel

   output reg [7:0] result,  //result
   output zero);

// a and b are 8 bit values stored in registers
always @(*)
begin
 case(alu_control)
 3'b000: result = a + b; // add
 3'b001: result = a - b; // sub
 3'b010: result = ~a;
 3'b011: result = a<<b;
 3'b100: result = a>>b;
 3'b101: result = a & b; // and
 3'b110: result = a | b; // or
 3'b111: begin if (a<b) result = 16'd1;
    else result = 16'd0;
    end
 default:result = a + b; // add
 endcase
end
assign zero = (result==16'd0) ? 1'b1: 1'b0;

endmodule

ALU_control.v
`timescale 1ns / 1ps

/*
Decode the ALU opcode based on the instruction Opcode.
See READ_ME.md for details.
ALU_op and ALU_cnt hold sufficient information to decide which Opcode to use
and whether or not to use the ALU in the first place.
*/

module alu_control( ALU_Cnt, ALUOp, Opcode);
 output reg[2:0] ALU_Cnt;
 input [1:0] ALUOp;
 input [3:0] Opcode;
 wire [5:0] ALUControlIn;
 assign ALUControlIn = {ALUOp,Opcode};
 always @(ALUControlIn)
 casex (ALUControlIn)
   6'b10xxxx: ALU_Cnt=3'b000;
   6'b01xxxx: ALU_Cnt=3'b001;
   6'b000010: ALU_Cnt=3'b000;
   6'b000011: ALU_Cnt=3'b001;
   6'b000100: ALU_Cnt=3'b010;
   6'b000101: ALU_Cnt=3'b011;
   6'b000110: ALU_Cnt=3'b100;
   6'b000111: ALU_Cnt=3'b101;
   6'b001000: ALU_Cnt=3'b110;
   6'b001001: ALU_Cnt=3'b111;
  default: ALU_Cnt=3'b000;
  endcase
endmodule

Register.v
`timescale 1ns / 1ps

`include "Parameter.v"

/*
Description:

GPRs module.
This is a set of 8 registers, each storing an 8 bit value.
There are 2 output values ra and rb,
whose values are selected based on the instruction word,
as in the instruction definitions given above.
There is one port by which data can be written into one of the registers,
but make sure to give an enable signal to control whether or not to update the value.
*/


module GPRs( //general purpose register
 input    clk,
 // write port
 input    reg_write_en,
 input  [2:0] reg_write_dest,
 input  [7:0] reg_write_data,
 //read port 1
 input  [2:0] reg_read_addr_1,
 output  [7:0] reg_read_data_1,
 //read port 2
 input  [2:0] reg_read_addr_2,
 output  [7:0] reg_read_data_2
);

 reg [7:0] reg_array [7:0];
 integer i;
 integer f;
 // write port
 //reg [2:0] i;
 initial begin
  for(i=0;i<8;i=i+1)
   reg_array[i] <= 8'd0;
 end

 initial
  begin
   f = $fopen(`filename);
   `simulation_time;
   $fclose(f);
  end

 always @ (posedge clk ) begin
 //output registers
 $monitor(f,"time = %d\n", $time,
 "\treg[0] = %b\n", reg_array[0],
 "\treg[1] = %b\n", reg_array[1],
 "\treg[2] = %b\n", reg_array[2],
 "\treg[3] = %b\n", reg_array[3],
 "\treg[4] = %b\n", reg_array[4],
 "\treg[5] = %b\n", reg_array[5],
 "\treg[6] = %b\n", reg_array[6],
 "\treg[7] = %b\n", reg_array[7]);

   if(reg_write_en) begin
    reg_array[reg_write_dest] <= reg_write_data;
   end
 end


 assign reg_read_data_1 = reg_array[reg_read_addr_1];
 assign reg_read_data_2 = reg_array[reg_read_addr_2];



endmodule

Datapath.v
`timescale 1ns / 1ps


/*
The unit that actually makes the entire processor work as expected.
The input to this is the instruction word,
and the output is a set of control signals
that decide, for example, whether the register file is to updated,
what operation is to be done by the ALU,
whether memory read or write is required etc.
*/

`include "Parameter.v"

module Data_Path(
      input[3:0] opcode,
      output reg[1:0] alu_op,
      output reg jump,beq,bne,mem_read,mem_write,alu_src,reg_dst,mem_to_reg,reg_write
    );
integer f; //log file

initial begin
f = $fopen(`filename);

  `simulation_time;
  $fclose(f);
end

always @(*)
begin
 $monitor(f,"time = %d\n", $time,"\n Opcode = %d\n",opcode);


 case(opcode)
 4'b0000:  // LW
   begin
    reg_dst = 1'b0;
    alu_src = 1'b1;
    mem_to_reg = 1'b1;
    reg_write = 1'b1;
    mem_read = 1'b1;
    mem_write = 1'b0;
    beq = 1'b0;
    bne = 1'b0;
    alu_op = 2'b10;
    jump = 1'b0;
   end
 4'b0001:  // SW
   begin
    reg_dst = 1'b0;
    alu_src = 1'b1;
    mem_to_reg = 1'b0;
    reg_write = 1'b0;
    mem_read = 1'b0;
    mem_write = 1'b1;
    beq = 1'b0;
    bne = 1'b0;
    alu_op = 2'b10;
    jump = 1'b0;
   end
 4'b0010:  // data_processing
   begin
    reg_dst = 1'b1;
    alu_src = 1'b0;
    mem_to_reg = 1'b0;
    reg_write = 1'b1;
    mem_read = 1'b0;
    mem_write = 1'b0;
    beq = 1'b0;
    bne = 1'b0;
    alu_op = 2'b00;
    jump = 1'b0;
   end
 4'b0011:  // data_processing
   begin
    reg_dst = 1'b1;
    alu_src = 1'b0;
    mem_to_reg = 1'b0;
    reg_write = 1'b1;
    mem_read = 1'b0;
    mem_write = 1'b0;
    beq = 1'b0;
    bne = 1'b0;
    alu_op = 2'b00;
    jump = 1'b0;
   end
 4'b0100:  // data_processing
   begin
    reg_dst = 1'b1;
    alu_src = 1'b0;
    mem_to_reg = 1'b0;
    reg_write = 1'b1;
    mem_read = 1'b0;
    mem_write = 1'b0;
    beq = 1'b0;
    bne = 1'b0;
    alu_op = 2'b00;
    jump = 1'b0;
   end
 4'b0101:  // data_processing
   begin
    reg_dst = 1'b1;
    alu_src = 1'b0;
    mem_to_reg = 1'b0;
    reg_write = 1'b1;
    mem_read = 1'b0;
    mem_write = 1'b0;
    beq = 1'b0;
    bne = 1'b0;
    alu_op = 2'b00;
    jump = 1'b0;
   end
 4'b0110:  // data_processing
   begin
    reg_dst = 1'b1;
    alu_src = 1'b0;
    mem_to_reg = 1'b0;
    reg_write = 1'b1;
    mem_read = 1'b0;
    mem_write = 1'b0;
    beq = 1'b0;
    bne = 1'b0;
    alu_op = 2'b00;
    jump = 1'b0;
   end
 4'b0111:  // data_processing
   begin
    reg_dst = 1'b1;
    alu_src = 1'b0;
    mem_to_reg = 1'b0;
    reg_write = 1'b1;
    mem_read = 1'b0;
    mem_write = 1'b0;
    beq = 1'b0;
    bne = 1'b0;
    alu_op = 2'b00;
    jump = 1'b0;
   end
 4'b1000:  // data_processing
   begin
    reg_dst = 1'b1;
    alu_src = 1'b0;
    mem_to_reg = 1'b0;
    reg_write = 1'b1;
    mem_read = 1'b0;
    mem_write = 1'b0;
    beq = 1'b0;
    bne = 1'b0;
    alu_op = 2'b00;
    jump = 1'b0;
   end
 4'b1001:  // data_processing
   begin
    reg_dst = 1'b1;
    alu_src = 1'b0;
    mem_to_reg = 1'b0;
    reg_write = 1'b1;
    mem_read = 1'b0;
    mem_write = 1'b0;
    beq = 1'b0;
    bne = 1'b0;
    alu_op = 2'b00;
    jump = 1'b0;
   end
 4'b1011:  // BEQ
   begin
    reg_dst = 1'b0;
    alu_src = 1'b0;
    mem_to_reg = 1'b0;
    reg_write = 1'b0;
    mem_read = 1'b0;
    mem_write = 1'b0;
    beq = 1'b1;
    bne = 1'b0;
    alu_op = 2'b01;
    jump = 1'b0;
   end
 4'b1100:  // BNE
   begin
    reg_dst = 1'b0;
    alu_src = 1'b0;
    mem_to_reg = 1'b0;
    reg_write = 1'b0;
    mem_read = 1'b0;
    mem_write = 1'b0;
    beq = 1'b0;
    bne = 1'b1;
    alu_op = 2'b01;
    jump = 1'b0;
   end
 4'b1101:  // J
   begin
    reg_dst = 1'b0;
    alu_src = 1'b0;
    mem_to_reg = 1'b0;
    reg_write = 1'b0;
    mem_read = 1'b0;
    mem_write = 1'b0;
    beq = 1'b0;
    bne = 1'b0;
    alu_op = 2'b00;
    jump = 1'b1;
   end
 default: begin
    reg_dst = 1'b1;
    alu_src = 1'b0;
    mem_to_reg = 1'b0;
    reg_write = 1'b1;
    mem_read = 1'b0;
    mem_write = 1'b0;
    beq = 1'b0;
    bne = 1'b0;
    alu_op = 2'b00;
    jump = 1'b0;
   end
 endcase
 end

endmodule

IMEM.v
`timescale 1ns / 1ps

/*
Description:

This can be a combinational unit - it takes just the address bus
(8 bit value) as input,
and gives out a 16-bit value that is the instruction to be decoded.
The address is provided by the Program Counter (PC).
*/

`include "Parameter.v"

module Instruction_Memory(
 input[`pc_length-1:0] pc,
 output[15:0] instruction
);

//for 16 bit processor

 reg [`col_memory - 1:0] instruction_memory [`row_i - 1:0];
 wire [$clog2(`col_memory)-1 : 0] rom_addr = pc[$clog2(`col_memory)-1 : 0];
 initial
 begin
  $readmemb(`program_file, instruction_memory,0,14);
 end
 assign instruction =  instruction_memory[rom_addr];

endmodule

Control.v
`timescale 1ns / 1ps

/*
Controls entire data flow.
See READ_ME for details.
Harvard Architecture.
*/

`include "Parameter.v"
`include "DMEM.v"
`include "ALU.v"
`include "ALU_control.v"
`include "IMEM.v"
`include "Register.v"
`include "Datapath.v"

module CU(
 input clk,
 output[15:0] pc_out,
 output [7:0] alu_result);

wire jump,bne,beq,mem_read,mem_write,alu_src,reg_dst,mem_to_reg,reg_write;
wire[1:0] alu_op;
wire [3:0] opcode;

 reg  [15:0] pc_current;            //Current PC
 wire [15:0] pc_next,pc2;           //Next two PC
 wire [15:0] instr;                 // instruction Opcode
 wire [2:0] reg_write_dest;         //Which reg to write
 wire [15:0] reg_write_data;        //Data to write
 wire [2:0] reg_read_addr_1;        //Which reg to read 1
 wire [15:0] reg_read_data_1;       //Data to read 1
 wire [2:0] reg_read_addr_2;        //Which reg to read 2
 wire [15:0] reg_read_data_2;       //Data to read 2
 wire [15:0] ext_im,read_data2;     //External instruction offset, Is Data to read (ALU vs immediate)
 wire [2:0] ALU_Control;            //ALU OPS
 wire [15:0] ALU_out;               //Result of ALU
 wire zero_flag;                    //zero flag
 wire [15:0] PC_j, PC_beq, PC_2beq,PC_2bne,PC_bne;    //Wires for JUMP, BNE, BEQ
 wire beq_control;
 wire [12:0] jump_shift;
 wire [15:0] mem_read_data;

 // Initilialise PC
 initial begin
  pc_current <= 16'd0;
 end

// Read Instruction
 always @(posedge clk)
 begin
   pc_current <= pc_next;
 end

 assign pc2 = pc_current + 16'd2;
 // instruction memory
 Instruction_Memory im(.pc(pc_current),.instruction(instr));
 // jump shift left 2
 assign jump_shift = {instr[11:0],1'b0};

 Data_Path data(opcode,
 alu_op,
jump,beq,bne,mem_read,mem_write,alu_src,reg_dst,mem_to_reg,reg_write
);
 // multiplexer regdest
 assign reg_write_dest = (reg_dst==1'b1) ? instr[5:3] :instr[8:6];
 // register file
 assign reg_read_addr_1 = instr[11:9];
 assign reg_read_addr_2 = instr[8:6];

///////////////////////////////

 // GENERAL PURPOSE REGISTERs
 GPRs reg_file
 (
  .clk(clk),
  .reg_write_en(reg_write),
  .reg_write_dest(reg_write_dest),
  .reg_write_data(reg_write_data),
  .reg_read_addr_1(reg_read_addr_1),
  .reg_read_data_1(reg_read_data_1),
  .reg_read_addr_2(reg_read_addr_2),
  .reg_read_data_2(reg_read_data_2)
 );

 // immediate extend
 assign ext_im = {{10{instr[5]}},instr[5:0]};   //record offset for load and store. The
 // ALU control unit
 alu_control ALU_Control_unit(.ALUOp(alu_op),.Opcode(instr[15:12]),.ALU_Cnt(ALU_Control));
 // multiplexer alu_src
 assign read_data2 = (alu_src==1'b1) ? ext_im : reg_read_data_2;
 // ALU
 ALU alu_unit(.a(reg_read_data_1),.b(read_data2),.alu_control(ALU_Control),.result(ALU_out),.zero(zero_flag));
 // PC beq add
 assign PC_beq = pc2 + {ext_im[14:0],1'b0};
 assign PC_bne = pc2 + {ext_im[14:0],1'b0};
 // beq control
 assign beq_control = beq & zero_flag;
 assign bne_control = bne & (~zero_flag);
 // PC_beq
 assign PC_2beq = (beq_control==1'b1) ? PC_beq : pc2;
 // PC_bne
 assign PC_2bne = (bne_control==1'b1) ? PC_bne : PC_2beq;
 // PC_j
 assign PC_j = {pc2[15:13],jump_shift};
 // PC_next
 assign pc_next = (jump == 1'b1) ? PC_j :  PC_2bne;

 /// Data memory
  Data_Memory dm
   (
    .clk(clk),
    .mem_access_addr(ALU_out),
    .mem_write_data(reg_read_data_2),
    .mem_write_en(mem_write),
    .mem_read(mem_read),
    .mem_read_data(mem_read_data)
   );

 // write back
 assign reg_write_data = (mem_to_reg == 1'b1)?  mem_read_data: ALU_out;
 // output to control unit
 assign opcode = instr[15:12];
 assign pc_out = pc_current;
 assign alu_result = ALU_out;  
endmodule

test_Control.v
`timescale 1ns / 1ps

/*
Testbench for RISC module
*/
`include "Parameter.v"
`include "Control.v"

module test_Risc_8_bit;

 // Inputs
 reg clk;
 wire [15:0] pc_out;
 wire [7:0] alu_result;

 // Instantiate the Unit Under Test (UUT)
 CU uut (
  clk,pc_out,alu_result
 );

 initial
  begin
  $dumpfile("./Waveforms/test_Control.vcd");
  $dumpvars(0, clk,pc_out,alu_result);

   clk <=0;
   `simulation_time;
   $finish;
  end

 always
  begin
   #5 clk = ~clk;
  end

endmodule

Waveforms/test_Control.vcd
$date
	Thu Nov  2 21:20:33 2017
$end
$version
	Icarus Verilog
$end
$timescale
	1ps
$end
$scope module test_Risc_8_bit $end
$var reg 1 ! clk $end
$upscope $end
$scope module test_Risc_8_bit $end
$var wire 16 " pc_out [15:0] $end
$upscope $end
$scope module test_Risc_8_bit $end
$var wire 8 # alu_result [7:0] $end
$upscope $end
$enddefinitions $end
#0
$dumpvars
b0 #
b0 "
0!
$end
#5000
b1 #
b10 "
1!
#10000
0!
#15000
b11 #
b100 "
1!
#20000
0!
#25000
b10 #
b110 "
1!
#30000
0!
#35000
b11111111 #
b1000 "
1!
#40000
0!
#45000
b11111110 #
b1010 "
1!
#50000
0!
#55000
b100 #
b1100 "
1!
#60000
0!
#65000
b0 #
b1110 "
1!
#70000
0!
#75000
b10000 "
1!
#80000
0!
#85000
b11 #
b10010 "
1!
#90000
0!
#95000
b1 #
b10100 "
1!
#100000
0!
#105000
b10 #
b10110 "
1!
#110000
0!
#115000
b0 #
b11000 "
1!
#120000
0!
#125000
b100 #
b11100 "
1!
#130000
0!
#135000
b1 #
b0 "
1!
#140000
0!
#145000
b10 #
b10 "
1!
#150000
0!
#155000
b101 #
b100 "
1!
#160000
0!
#165000
b11 #
b110 "
1!
#170000
0!
#175000
b11111111 #
b1000 "
1!
#180000
0!
#185000
b11111101 #
b1010 "
1!
#190000
0!
#195000
b10000 #
b1100 "
1!
#200000
0!
#205000
b0 #
b1110 "
1!
#210000
0!
#215000
b10 #
b10000 "
1!
#220000
0!
#225000
b11 #
b10010 "
1!
#230000
0!
#235000
b1 #
b10100 "
1!
#240000
0!
#245000
b100 #
b10110 "
1!
#250000
0!
#255000
b1 #
b11000 "
1!
#260000
0!
#265000
b11010 "
1!
#270000
0!
#275000
b1000 #
b11100 "
1!
#280000
0!
#285000
b1 #
b0 "
1!
#290000
0!
#295000
b10 #
b10 "
1!
