Parameter.v
`timescale 1ns / 1ps

`ifndef PARAMETER_H_
`define PARAMETER_H_

// Parameter file
`define col 8 // 8 bits data memory.
`define col_memory 16 // 16 bits instruction memory.
`define row_i 15 // instruction memory, instructions number, this number can be changed. Adding more instructions to verify your design is a good idea.
`define row_d 8 // The number of data registers in data memory.
//We only use 8 data. Do not change this number.
// Please only change the value of each data inside test.data file. Total number is fixed at 8.
`define filename "./demo/1_11_17_16_44.o"
`define simulation_time #300
`define data_file "./demo/data.txt"
`define program_file "./demo/prog.txt"
`endif

ALU.v
//ALU

module ALU (
  input  [7:0] a,  //src1
   input  [7:0] b,  //src2
   input  [2:0] alu_control, //function sel

   output reg [7:0] result,  //result
   output zero);

// a and b are 8 bit values stored in registers
always @(*)
begin
 case(alu_control)
 3'b000: result = a + b; // add
 3'b001: result = a - b; // sub
 3'b010: result = ~a;
 3'b011: result = a<<b;
 3'b100: result = a>>b;
 3'b101: result = a & b; // and
 3'b110: result = a | b; // or
 3'b111: begin if (a<b) result = 16'd1;
    else result = 16'd0;
    end
 default:result = a + b; // add
 endcase
end
assign zero = (result==16'd0) ? 1'b1: 1'b0;

endmodule

test_ALU.v
`timescale 1ns / 1ps

/*
Testbench for RISC module
*/
`include "Parameter.v"
`include "ALU.v"

module test_ALU;

 // Inputs
 reg [7:0] a;
 reg  [7:0] b;
 reg [2:0] cnt;
 wire [7:0] c;
 wire zero;

 // Instantiate the Unit Under Test (UUT)
 ALU uut (a,b,cnt,c,zero
 );

 initial
  begin

  $dumpfile("./Waveforms/test_ALU.vcd");
  $dumpvars(0, a,b,cnt,c,zero);

   a=8'd0;
   b=8'd0;
   cnt=3'd0;

   #20 begin
   a=8'd2;
   b=8'd5;
   cnt=3'd0;
   end

   #30 begin
   a=8'd10;
   b=8'd13;
   cnt=3'd0;
   end

   #40 begin

   a=8'd2;
   b=8'd1;
   cnt=3'd1;

   end

   #50 begin
   a=8'd10;
   b=8'd13;
   cnt=3'd2;
   end

   #60 begin
   a=8'd10;
   b=8'd13;
   cnt=3'd3;
   end

   #70 begin
   a=8'd10;
   b=8'd13;
   cnt=3'd4;
   end

   #80 begin
   a=8'd10;
   b=8'd13;
   cnt=3'd5;
   end

   #90 begin
   a=8'd10;
   b=8'd13;
   cnt=3'd6;
   end

   #100 begin
   a=8'd10;
   b=8'd13;
   cnt=3'd7;
   end

   #110 begin
   a=8'd2;
   b=8'd5;
   cnt=3'd0;
   end


   `simulation_time;
   $finish;
  end

endmodule

Waveforms/test_ALU.vcd
$date
	Thu Nov  2 11:50:17 2017
$end
$version
	Icarus Verilog
$end
$timescale
	1ps
$end
$scope module test_ALU $end
$var reg 8 ! a [7:0] $end
$upscope $end
$scope module test_ALU $end
$var reg 8 " b [7:0] $end
$upscope $end
$scope module test_ALU $end
$var reg 3 # cnt [2:0] $end
$upscope $end
$scope module test_ALU $end
$var wire 8 $ c [7:0] $end
$upscope $end
$scope module test_ALU $end
$var wire 1 % zero $end
$upscope $end
$enddefinitions $end
#0
$dumpvars
1%
b0 $
b0 #
b0 "
b0 !
$end
#20000
0%
b111 $
b101 "
b10 !
#50000
b10111 $
b1101 "
b1010 !
#90000
b1 $
b1 #
b1 "
b10 !
#140000
b11110101 $
b10 #
b1101 "
b1010 !
#200000
1%
b0 $
b11 #
#270000
b100 #
#350000
0%
b1000 $
b101 #
#440000
b1111 $
b110 #
#540000
b1 $
b111 #
#650000
b111 $
b0 #
b101 "
b10 !
