Parameter.v

`ifndef PARAMETER_H_
`define PARAMETER_H_

// Parameter file
`define col 8 // 8 bits data memory.
`define col_memory 16 // 16 bits instruction memory.
`define row_i 15 // instruction memory, instructions number, this number can be changed. Adding more instructions to verify your design is a good idea.
`define row_d 8 // The number of data registers in data memory.
//We only use 8 data. Do not change this number.
// Please only change the value of each data inside test.data file. Total number is fixed at 8.
`define filename "./test/factorial.o"
`define waveform_output "./test/factorial.vcd"
`define simulation_time #10000
`define data_file "./test/data_factorial.txt"
`define program_file "./test/factorial_prog.txt"
`define pc_length 8 //length of program counter
`endif

DMEM.v
`timescale 1ns / 1ps

/*
Description:
This needs to be a sequential / clocked unit.
At any given cycle, you are either reading from it
or writing to it, with the address given by the address bus.
In case of a lw (load-word) or sw (store-word) instruction,
the address is either immediate or the output of the ALU.
The data output of the DMEM will always go into the register file,
where it gets stored into a register selected by rd.
*/

`include "Parameter.v"

module Data_Memory(
 input clk,
 // address input, shared by read and write port
 input [7:0]   mem_access_addr,

 // write port
 input [7:0]   mem_write_data,
 input     mem_write_en,
 input mem_read,
 // read port
 output [7:0]   mem_read_data
);

reg [`col - 1:0] memory [`row_d - 1:0];   //registers
integer f;
wire [2:0] ram_addr=mem_access_addr[2:0];

initial
 begin
  $readmemb(`data_file, memory);

  f = $fopen(`filename);

  `simulation_time;
  $fclose(f);
 end

 always @(posedge clk) begin
  $fmonitor(f, "time = %d\n", $time,
  "\tmemory[0] = %b\n", memory[0],
  "\tmemory[1] = %b\n", memory[1],
  "\tmemory[2] = %b\n", memory[2],
  "\tmemory[3] = %b\n", memory[3],
  "\tmemory[4] = %b\n", memory[4],
  "\tmemory[5] = %b\n", memory[5],
  "\tmemory[6] = %b\n", memory[6],
  "\tmemory[7] = %b\n", memory[7]);
end

always @(posedge clk) begin
  if (mem_write_en)
   memory[ram_addr] <= mem_write_data;
end
assign mem_read_data = (mem_read==1'b1) ? memory[ram_addr]: 8'd0;

endmodule

ALU.v
//ALU

module ALU (
  input  [7:0] a,  //src1
   input  [7:0] b,  //src2
   input  [2:0] alu_control, //function sel

   output reg [7:0] result,  //result
   output zero);

// a and b are 8 bit values stored in registers
always @(*)
begin
 case(alu_control)
 3'b000: result = a + b; // add
 3'b001: result = a - b; // sub
 3'b010: result = ~a;
 3'b011: result = a<<b;
 3'b100: result = a>>b;
 3'b101: result = a & b; // and
 3'b110: result = a | b; // or
 3'b111: begin if (a<b) result = 16'd1;
    else result = 16'd0;
    end
 default:result = a + b; // add
 endcase
end
assign zero = (result==16'd0) ? 1'b1: 1'b0;

endmodule

Register.v
`timescale 1ns / 1ps

`include "Parameter.v"

/*
Description:

GPRs module.
This is a set of 8 registers, each storing an 8 bit value.
There are 2 output values ra and rb,
whose values are selected based on the instruction word,
as in the instruction definitions given above.
There is one port by which data can be written into one of the registers,
but make sure to give an enable signal to control whether or not to update the value.
*/


module GPRs( //general purpose register
 input    clk,
 // write port
 input    reg_write_en,
 input  [2:0] reg_write_dest,
 input  [7:0] reg_write_data,
 //read port 1
 input  [2:0] reg_read_addr_1,
 output  [7:0] reg_read_data_1,
 //read port 2
 input  [2:0] reg_read_addr_2,
 output  [7:0] reg_read_data_2
);

 reg [7:0] reg_array [7:0];
 integer i;
 integer f;
 // write port
 //reg [2:0] i;
 initial begin
  for(i=0;i<8;i=i+1)
   reg_array[i] <= 8'd0;
 end

 initial
  begin
   f = $fopen(`filename);
   `simulation_time;
   $fclose(f);
  end

 always @ (posedge clk ) begin
 //output registers
 $monitor(f,"time = %d\n", $time,
 "\treg[0] = %b\n", reg_array[0],
 "\treg[1] = %b\n", reg_array[1],
 "\treg[2] = %b\n", reg_array[2],
 "\treg[3] = %b\n", reg_array[3],
 "\treg[4] = %b\n", reg_array[4],
 "\treg[5] = %b\n", reg_array[5],
 "\treg[6] = %b\n", reg_array[6],
 "\treg[7] = %b\n", reg_array[7]);

   if(reg_write_en) begin
    reg_array[reg_write_dest] <= reg_write_data;
   end
 end


 assign reg_read_data_1 = reg_array[reg_read_addr_1];
 assign reg_read_data_2 = reg_array[reg_read_addr_2];



endmodule

IMEM.v
`timescale 1ns / 1ps

/*
Description:

This can be a combinational unit - it takes just the address bus
(8 bit value) as input,
and gives out a 16-bit value that is the instruction to be decoded.
The address is provided by the Program Counter (PC).
*/

`include "Parameter.v"

module Instruction_Memory(
 input[15:0] pc,
 output[15:0] instruction
);

//for 16 bit processor

 reg [`col_memory - 1:0] instruction_memory [`row_i - 1:0];
 wire [3 : 0] rom_addr = pc[4 : 1];
 initial
 begin
  $readmemb(`program_file, instruction_memory,0,14);
 end
 assign instruction =  instruction_memory[rom_addr];

endmodule

PC.v
module ProgramCounter
(
input [7:0]d_in,
input reset, clk,jump,branch,hold,
input [6:0] branch_immem,
input [6:0] jump_line,
output reg [7:0] d_out
);

`include "Parameter.v"

/*
8 bit register.
 Under normal operations, will always increment by 1 on every clock cycle,
to access the next instruction. In case of a JUMP or BRANCH type of instruction,
 will go to the value specified by the output of the ALU
or the immediate operand in the instruction.

*/

//if hold then only operate

always @(clk) begin
if (hold==1'b0) begin
  if (reset)
  d_out <= 8'b00000000;
  else if (jump)
  d_out<=jump_line*2; //jump_line is 7 bits length
  else if (branch)
  d_out<=d_in + {2'b00,branch_immem}; //immem is max 6 bits long
  else if (d_in== `col_memory)
  d_out<=d_in;        //EOP
  else
  d_out <= d_in + 1;
end

else
d_out<=d_in;
end
endmodule

CU.v
`timescale 1ns / 1ps

/*
Controls entire data flow.
See READ_ME for details.
Harvard Architecture.
*/

`include "Parameter.v"
`include "DMEM.v"
`include "ALU.v"
`include "IMEM.v"
`include "Register.v"
`include "PC.v"

module CU(
 input clk,
 input reset,
 output[15:0] pc_out,
 output [7:0] alu_result,
 output reg [2:0] state,
 output reg hold,
 output [3:0] opcode);

//for PC
reg [7:0] pc_current;
wire [7:0] pc_next;
reg [6:0] branch_immem;
reg [6:0] jump_line;
reg jump,branch,mem_write,alu_src,mem_to_reg,reg_write;
//reg hold;

//for imem
wire [15:0] instruction;

//for GPRu
reg    WR,RA;
reg  [2:0] rd;
reg  [7:0] rd_data;
reg  [2:0] ra;
wire [7:0] ra_data;
reg  [2:0] rb;
wire [7:0] rb_data;

//for ALU
reg [2:0] alu_control;
reg [7:0] a,b;
wire [7:0] result;
wire zero;

//for DMEM
reg [7:0] mem_access_addr;
reg [7:0] mem_write_data;
reg mem_write_en;
reg mem_read;
wire [7:0] mem_read_data;

//for CU
//reg [3:0] opcode;
//reg [2:0] state;
reg [5:0] imm;

ProgramCounter PC(pc_current,reset, clk,jump,branch,hold,branch_immem,jump_line,pc_next);

Instruction_Memory IM(.pc(pc_current),.instruction(instruction));

GPRs REG(clk,WR, RA,rd,rd_data,ra,ra_data,rb,rb_data);

ALU alu_unit(a,b,alu_control,result,zero);

Data_Memory DM(clk,mem_access_addr,mem_write_data,mem_write_en,mem_read,mem_read_data);

assign opcode = instruction[15:12];

initial begin
pc_current=0;
hold=0;
state=0;
end

always @(posedge clk)
begin


case(opcode)
4'b0000: begin      //ALU direct data processing
  //hold=1;
  rd=instruction[11:9];
  ra=instruction[8:6];
  rb=instruction[5:3];
  alu_control=instruction[2:0];
  {jump,branch,mem_write,alu_src,mem_to_reg,reg_write}=6'b000001;

  case(state)
  3'b000: begin      //read ra, rb from Instructions
    hold=1;
    RA=1;
    state=state+1;
  end
  3'b001: begin      //allow ALU to process
    RA=0;
    a=ra_data;
    b=rb_data;
    state=state+1;
  end
  3'b010: begin      //allow ALU to process
    rd_data=result;
    state=state+1;
    WR=1;
  end
  3'b011: begin        //write to register
    state=state+1;
    hold=0;
  end
  3'b100: begin
    WR=0;
    state=0;
    hold=1;
  end
  endcase
end

4'b0100:
  begin      //addi rd<=ra+imm
  //hold=1;
  ra=instruction[8:6];
  rd=instruction[5:3];
  imm={instruction[11:9],instruction[2:0]};
  alu_control=0;
  {jump,branch,mem_write,alu_src,mem_to_reg,reg_write}=6'b000001;

  case(state)
  3'b000: begin        //read ra, imem from Instructions
    hold=1;
    RA=1;
    state=state+1;
  end
  3'b001: begin        //process with ALU
    RA=0;
    a=ra_data;
    b={2'b00,imm};
    state=state+1;
  end
  3'b010: begin        //write to register
    rd_data=result;
    state=state+1;
    WR=1;
  end
  3'b011: begin        //write to register

    state=state+1;
    hold=0;
  end
  3'b100:
  begin        //one cycle for latency
    WR=0;
    state=0;
    hold=1;
  end
  endcase
end


4'b1011: begin      //load value.
//  hold=1;
  ra=instruction[8:6];
  rd=instruction[5:3];
  imm={instruction[11:9],instruction[2:0]};
  alu_control=0;
  {jump,branch,mem_write,alu_src,mem_to_reg,reg_write}=6'b000111;

  case(state)
  3'b000: begin        //read ra, imem from Instructions
    hold=1;
    RA=1;
    state=state+1;
  end
  3'b001: begin        //read from memory
    RA=0;
    mem_access_addr=ra_data+{2'b00,imm};
    state=state+1;
  end
  3'b010: begin        //read from memory
    mem_read=1;
    state=state+1;
  end
  3'b011: begin        //write to register rd
    rd_data=mem_read_data;
    mem_read=0;
    state=state+1;
  end
  3'b100: begin        //write to register rd
    WR=1;
    state=state+1;
    hold=0;
  end
  3'b101:
  begin        //one cycle for latency
    WR=0;
    state=0;
    hold=1;
  end
  endcase
end

4'b1111: begin       //store value
  //hold=1;
  ra=instruction[8:6];
  rb=instruction[5:3];
  imm={instruction[11:9],instruction[2:0]};
  alu_control=0;
  {jump,branch,mem_write,alu_src,mem_to_reg,reg_write}=6'b001100;

  case(state)
  3'b000: begin        //read ra,rb imem from Instructions
    hold=1;
    RA=1;
    state=state+1;
  end
  3'b001: begin        //write to data mem
    mem_access_addr=ra_data+{2'b00,imm};
    $display("memory access",mem_access_addr);
    state=state+1;
  end
  3'b010: begin        //latency
    RA=0;
    mem_write_data=rb_data;
    $display("data",rb_data);
    $display("source",rb);
    mem_write_en=1;
    state=state+1;
  end
  3'b011: begin        //latency
    state=state+1;
    hold=0;
  end
  3'b100: begin        //latency
    mem_write_en=0;
    state=0;
    hold=1;
  end
  endcase

end

4'b1000: begin      //branch if equal
  //hold=1;
  ra=instruction[8:6];
  rb=instruction[5:3];
  imm={instruction[11:9],instruction[2:0]};
  alu_control=3'b111;
  {jump,branch,mem_write,alu_src,mem_to_reg,reg_write}=6'b010000;

  case(state)
  3'b000: begin      //read ra, rb from Instructions
    hold=1;
    RA=1;
    state=state+1;
  end
  3'b001: begin      //allow ALU to process
    RA=0;
    a=ra_data;
    b=rb_data;
    state=state+1;
  end
  3'b010: begin        //update pc
    if (zero)
      branch_immem=imm;
    else
      branch=0;
    state=state+1;
    hold=0;
  end
  3'b011: begin     //release all holds
    branch=0;
    state=0;
    hold=1;
  end
endcase

end

4'b0010: begin        //jump
  case(state)
  3'b000: begin
  hold=0;
  {jump,branch,mem_write,alu_src,mem_to_reg,reg_write}=6'b100000;
  jump_line=instruction[6:0];
  state=state+1;
  end
  3'b001: begin
  hold=1;
  jump=0;
  state=0;
  end
  endcase
end

4'b0111: begin
  $display("End Of Program");
  hold=1;
end

endcase

pc_current=pc_next;
end

 assign pc_out = pc_current;
 assign alu_result = result;
endmodule

test_CU_n.v
`timescale 1ns / 1ps

/*
Testbench for RISC module
*/
`include "Parameter.v"
`include "CU.v"

module test_CU;

 // Inputs
 reg clk;
 reg reset;
 wire [15:0] pc_out;
 wire [7:0] alu_result;
 wire [2:0] state;
 wire hold;
 wire [3:0] opcode;
 wire zero;

 // Instantiate the Unit Under Test (UUT)
 CU uut (
  clk,reset,pc_out,alu_result,state,hold,opcode,zero
 );

 initial
  begin
  reset=1;
  $dumpfile(`waveform_output);
  $dumpvars(0, clk,reset,pc_out,alu_result,state,hold,opcode,zero);

   clk <=0;
   `simulation_time;
   $finish;
  end

 always
  begin
   #5 clk = ~clk; reset=0;
  end

endmodule

test/factorial.vcd
$date
	Thu Nov  9 11:42:37 2017
$end
$version
	Icarus Verilog
$end
$timescale
	1ps
$end
$scope module test_CU $end
$var reg 1 ! clk $end
$upscope $end
$scope module test_CU $end
$var reg 1 " reset $end
$upscope $end
$scope module test_CU $end
$var wire 16 # pc_out [15:0] $end
$upscope $end
$scope module test_CU $end
$var wire 8 $ alu_result [7:0] $end
$upscope $end
$scope module test_CU $end
$var wire 3 % state [2:0] $end
$upscope $end
$scope module test_CU $end
$var wire 1 & hold $end
$upscope $end
$scope module test_CU $end
$var wire 4 ' opcode [3:0] $end
$upscope $end
$scope module test_CU $end
$var wire 1 ( zero $end
$upscope $end
$enddefinitions $end
#0
$dumpvars
x(
b1011 '
0&
b0 %
bx $
b0 #
1"
0!
$end
#5000
b1 %
1&
0"
1!
#10000
0!
#15000
b10 %
1!
#20000
0!
#25000
b11 %
1!
#30000
0!
#35000
b100 %
1!
#40000
0!
#45000
0&
b101 %
1!
#50000
0!
#55000
b1 #
1&
b0 %
1!
#60000
0!
#65000
b1 %
1!
#70000
0!
#75000
b10 %
1!
#80000
0!
#85000
b11 %
1!
#90000
0!
#95000
b100 %
1!
#100000
0!
#105000
0&
b101 %
1!
#110000
0!
#115000
b10 #
1&
b0 %
1!
#120000
0!
#125000
b1 %
1!
#130000
0!
#135000
b10 %
1!
#140000
0!
#145000
b11 %
1!
#150000
0!
#155000
b100 %
1!
#160000
0!
#165000
0&
b101 %
1!
#170000
0!
#175000
b0 '
b11 #
1&
b0 %
1!
#180000
0!
#185000
b1 %
1!
#190000
0!
#195000
b10 %
1!
#200000
0!
#205000
1(
b0 $
b11 %
1!
#210000
0!
#215000
b100 %
1!
#220000
0!
#225000
b101 %
1!
#230000
0!
#235000
b110 %
1!
#240000
0!
#245000
0&
b111 %
1!
#250000
0!
#255000
b100 #
1&
b0 %
1!
#260000
0!
#265000
b1 %
1!
#270000
0!
#275000
b10 %
1!
#280000
0!
#285000
0(
b101 $
b11 %
1!
#290000
0!
#295000
b100 %
1!
#300000
0!
#305000
b101 %
1!
#310000
0!
#315000
b110 %
1!
#320000
0!
#325000
0&
b111 %
1!
#330000
0!
#335000
b101 #
1&
b0 %
1!
#340000
0!
#345000
b1 %
1!
#350000
0!
#355000
b10 %
1!
#360000
0!
#365000
1(
b0 $
b11 %
1!
#370000
0!
#375000
b100 %
1!
#380000
0!
#385000
b101 %
1!
#390000
0!
#395000
b110 %
1!
#400000
0!
#405000
0&
b111 %
1!
#410000
0!
#415000
b100 '
b110 #
1&
b0 %
1!
#420000
0!
#425000
b1 %
1!
#430000
0!
#435000
b10 %
1!
#440000
0!
#445000
0(
b1 $
b11 %
1!
#450000
0!
#455000
b100 %
1!
#460000
0!
#465000
b101 %
1!
#470000
0!
#475000
b110 %
1!
#480000
0!
#485000
0&
b111 %
1!
#490000
0!
#495000
b1000 '
b111 #
1&
b0 %
1!
#500000
0!
#505000
b11111111 $
b1 %
1!
#510000
0!
#515000
b10 %
1!
#520000
0!
#525000
b1 $
b11 %
1!
#530000
0!
#535000
0&
b100 %
1!
#540000
0!
#545000
b10 '
b1000 #
1&
b0 %
1!
#550000
0!
#555000
b1 %
0&
1!
#560000
0!
#565000
b0 '
b100 #
b0 %
1&
1!
#570000
0!
#575000
b11 $
b1 %
1!
#580000
0!
#585000
b10 %
1!
#590000
0!
#595000
b1010 $
b11 %
1!
#600000
0!
#605000
b100 %
1!
#610000
0!
#615000
b101 %
1!
#620000
0!
#625000
b110 %
1!
#630000
0!
#635000
0&
b111 %
1!
#640000
0!
#645000
b101 #
1&
b0 %
1!
#650000
0!
#655000
b1 %
1!
#660000
0!
#665000
b10 %
1!
#670000
0!
#675000
1(
b0 $
b11 %
1!
#680000
0!
#685000
b100 %
1!
#690000
0!
#695000
b101 %
1!
#700000
0!
#705000
b110 %
1!
#710000
0!
#715000
0&
b111 %
1!
#720000
0!
#725000
b100 '
b110 #
1&
b0 %
1!
#730000
0!
#735000
b1 %
1!
#740000
0!
#745000
b10 %
1!
#750000
0!
#755000
0(
b10 $
b11 %
1!
#760000
0!
#765000
b100 %
1!
#770000
0!
#775000
b101 %
1!
#780000
0!
#785000
b110 %
1!
#790000
0!
#795000
0&
b111 %
1!
#800000
0!
#805000
b1000 '
b111 #
1&
b0 %
1!
#810000
0!
#815000
1(
b0 $
b1 %
1!
#820000
0!
#825000
b10 %
1!
#830000
0!
#835000
b11 %
1!
#840000
0!
#845000
0&
b100 %
1!
#850000
0!
#855000
b0 '
b1001 #
1&
b0 %
1!
#860000
0!
#865000
0(
b100 $
b1 %
1!
#870000
0!
#875000
b10 %
1!
#880000
0!
#885000
b1010 $
b11 %
1!
#890000
0!
#895000
b100 %
1!
#900000
0!
#905000
b101 %
1!
#910000
0!
#915000
b110 %
1!
#920000
0!
#925000
0&
b111 %
1!
#930000
0!
#935000
b1010 #
1&
b0 %
1!
#940000
0!
#945000
b1 %
1!
#950000
0!
#955000
b10 %
1!
#960000
0!
#965000
1(
b0 $
b11 %
1!
#970000
0!
#975000
b100 %
1!
#980000
0!
#985000
b101 %
1!
#990000
0!
#995000
b110 %
1!
#1000000
0!
#1005000
0&
b111 %
1!
#1010000
0!
#1015000
b100 '
b1011 #
1&
b0 %
1!
#1020000
0!
#1025000
b1 %
1!
#1030000
0!
#1035000
b10 %
1!
#1040000
0!
#1045000
0(
b11 $
b11 %
1!
#1050000
0!
#1055000
b100 %
1!
#1060000
0!
#1065000
b101 %
1!
#1070000
0!
#1075000
b110 %
1!
#1080000
0!
#1085000
0&
b111 %
1!
#1090000
0!
#1095000
b1000 '
b1100 #
1&
b0 %
1!
#1100000
0!
#1105000
b1 $
b1 %
1!
#1110000
0!
#1115000
b10 %
1!
#1120000
0!
#1125000
b10 $
b11 %
1!
#1130000
0!
#1135000
0&
b100 %
1!
#1140000
0!
#1145000
b10 '
b1101 #
1&
b0 %
1!
#1150000
0!
#1155000
b1 %
0&
1!
#1160000
0!
#1165000
b0 '
b11 #
b0 %
1&
1!
#1170000
0!
#1175000
b1000 $
b1 %
1!
#1180000
0!
#1185000
b10 %
1!
#1190000
0!
#1195000
1(
b0 $
b11 %
1!
#1200000
0!
#1205000
b100 %
1!
#1210000
0!
#1215000
b101 %
1!
#1220000
0!
#1225000
b110 %
1!
#1230000
0!
#1235000
0&
b111 %
1!
#1240000
0!
#1245000
b100 #
1&
b0 %
1!
#1250000
0!
#1255000
b1 %
1!
#1260000
0!
#1265000
b10 %
1!
#1270000
0!
#1275000
0(
b1010 $
b11 %
1!
#1280000
0!
#1285000
b100 %
1!
#1290000
0!
#1295000
b101 %
1!
#1300000
0!
#1305000
b110 %
1!
#1310000
0!
#1315000
0&
b111 %
1!
#1320000
0!
#1325000
b101 #
1&
b0 %
1!
#1330000
0!
#1335000
b1 %
1!
#1340000
0!
#1345000
b10 %
1!
#1350000
0!
#1355000
1(
b0 $
b11 %
1!
#1360000
0!
#1365000
b100 %
1!
#1370000
0!
#1375000
b101 %
1!
#1380000
0!
#1385000
b110 %
1!
#1390000
0!
#1395000
0&
b111 %
1!
#1400000
0!
#1405000
b100 '
b110 #
1&
b0 %
1!
#1410000
0!
#1415000
b1 %
1!
#1420000
0!
#1425000
b10 %
1!
#1430000
0!
#1435000
0(
b1 $
b11 %
1!
#1440000
0!
#1445000
b100 %
1!
#1450000
0!
#1455000
b101 %
1!
#1460000
0!
#1465000
b110 %
1!
#1470000
0!
#1475000
0&
b111 %
1!
#1480000
0!
#1485000
b1000 '
b111 #
1&
b0 %
1!
#1490000
0!
#1495000
b11111111 $
b1 %
1!
#1500000
0!
#1505000
b10 %
1!
#1510000
0!
#1515000
b10 $
b11 %
1!
#1520000
0!
#1525000
0&
b100 %
1!
#1530000
0!
#1535000
b10 '
b1000 #
1&
b0 %
1!
#1540000
0!
#1545000
b1 %
0&
1!
#1550000
0!
#1555000
b0 '
b100 #
b0 %
1&
1!
#1560000
0!
#1565000
b100 $
b1 %
1!
#1570000
0!
#1575000
b10 %
1!
#1580000
0!
#1585000
b10100 $
b11 %
1!
#1590000
0!
#1595000
b100 %
1!
#1600000
0!
#1605000
b101 %
1!
#1610000
0!
#1615000
b110 %
1!
#1620000
0!
#1625000
0&
b111 %
1!
#1630000
0!
#1635000
b101 #
1&
b0 %
1!
#1640000
0!
#1645000
b1 %
1!
#1650000
0!
#1655000
b10 %
1!
#1660000
0!
#1665000
1(
b0 $
b11 %
1!
#1670000
0!
#1675000
b100 %
1!
#1680000
0!
#1685000
b101 %
1!
#1690000
0!
#1695000
b110 %
1!
#1700000
0!
#1705000
0&
b111 %
1!
#1710000
0!
#1715000
b100 '
b110 #
1&
b0 %
1!
#1720000
0!
#1725000
b1 %
1!
#1730000
0!
#1735000
b10 %
1!
#1740000
0!
#1745000
0(
b10 $
b11 %
1!
#1750000
0!
#1755000
b100 %
1!
#1760000
0!
#1765000
b101 %
1!
#1770000
0!
#1775000
b110 %
1!
#1780000
0!
#1785000
0&
b111 %
1!
#1790000
0!
#1795000
b1000 '
b111 #
1&
b0 %
1!
#1800000
0!
#1805000
1(
b0 $
b1 %
1!
#1810000
0!
#1815000
b10 %
1!
#1820000
0!
#1825000
0(
b1 $
b11 %
1!
#1830000
0!
#1835000
0&
b100 %
1!
#1840000
0!
#1845000
b10 '
b1000 #
1&
b0 %
1!
#1850000
0!
#1855000
b1 %
0&
1!
#1860000
0!
#1865000
b0 '
b100 #
b0 %
1&
1!
#1870000
0!
#1875000
b101 $
b1 %
1!
#1880000
0!
#1885000
b10 %
1!
#1890000
0!
#1895000
b11110 $
b11 %
1!
#1900000
0!
#1905000
b100 %
1!
#1910000
0!
#1915000
b101 %
1!
#1920000
0!
#1925000
b110 %
1!
#1930000
0!
#1935000
0&
b111 %
1!
#1940000
0!
#1945000
b101 #
1&
b0 %
1!
#1950000
0!
#1955000
b1 %
1!
#1960000
0!
#1965000
b10 %
1!
#1970000
0!
#1975000
1(
b0 $
b11 %
1!
#1980000
0!
#1985000
b100 %
1!
#1990000
0!
#1995000
b101 %
1!
#2000000
0!
#2005000
b110 %
1!
#2010000
0!
#2015000
0&
b111 %
1!
#2020000
0!
#2025000
b100 '
b110 #
1&
b0 %
1!
#2030000
0!
#2035000
b1 %
1!
#2040000
0!
#2045000
b10 %
1!
#2050000
0!
#2055000
0(
b11 $
b11 %
1!
#2060000
0!
#2065000
b100 %
1!
#2070000
0!
#2075000
b101 %
1!
#2080000
0!
#2085000
b110 %
1!
#2090000
0!
#2095000
0&
b111 %
1!
#2100000
0!
#2105000
b1000 '
b111 #
1&
b0 %
1!
#2110000
0!
#2115000
b1 $
b1 %
1!
#2120000
0!
#2125000
b10 %
1!
#2130000
0!
#2135000
1(
b0 $
b11 %
1!
#2140000
0!
#2145000
0&
b100 %
1!
#2150000
0!
#2155000
b0 '
b1001 #
1&
b0 %
1!
#2160000
0!
#2165000
0(
b110 $
b1 %
1!
#2170000
0!
#2175000
b10 %
1!
#2180000
0!
#2185000
b11110 $
b11 %
1!
#2190000
0!
#2195000
b100 %
1!
#2200000
0!
#2205000
b101 %
1!
#2210000
0!
#2215000
b110 %
1!
#2220000
0!
#2225000
0&
b111 %
1!
#2230000
0!
#2235000
b1010 #
1&
b0 %
1!
#2240000
0!
#2245000
b1 %
1!
#2250000
0!
#2255000
b10 %
1!
#2260000
0!
#2265000
1(
b0 $
b11 %
1!
#2270000
0!
#2275000
b100 %
1!
#2280000
0!
#2285000
b101 %
1!
#2290000
0!
#2295000
b110 %
1!
#2300000
0!
#2305000
0&
b111 %
1!
#2310000
0!
#2315000
b100 '
b1011 #
1&
b0 %
1!
#2320000
0!
#2325000
b1 %
1!
#2330000
0!
#2335000
b10 %
1!
#2340000
0!
#2345000
0(
b100 $
b11 %
1!
#2350000
0!
#2355000
b100 %
1!
#2360000
0!
#2365000
b101 %
1!
#2370000
0!
#2375000
b110 %
1!
#2380000
0!
#2385000
0&
b111 %
1!
#2390000
0!
#2395000
b1000 '
b1100 #
1&
b0 %
1!
#2400000
0!
#2405000
b10 $
b1 %
1!
#2410000
0!
#2415000
b10 %
1!
#2420000
0!
#2425000
b1 $
b11 %
1!
#2430000
0!
#2435000
0&
b100 %
1!
#2440000
0!
#2445000
b10 '
b1101 #
1&
b0 %
1!
#2450000
0!
#2455000
b1 %
0&
1!
#2460000
0!
#2465000
b0 '
b11 #
b0 %
1&
1!
#2470000
0!
#2475000
b1001 $
b1 %
1!
#2480000
0!
#2485000
b10 %
1!
#2490000
0!
#2495000
1(
b0 $
b11 %
1!
#2500000
0!
#2505000
b100 %
1!
#2510000
0!
#2515000
b101 %
1!
#2520000
0!
#2525000
b110 %
1!
#2530000
0!
#2535000
0&
b111 %
1!
#2540000
0!
#2545000
b100 #
1&
b0 %
1!
#2550000
0!
#2555000
b1 %
1!
#2560000
0!
#2565000
b10 %
1!
#2570000
0!
#2575000
0(
b11110 $
b11 %
1!
#2580000
0!
#2585000
b100 %
1!
#2590000
0!
#2595000
b101 %
1!
#2600000
0!
#2605000
b110 %
1!
#2610000
0!
#2615000
0&
b111 %
1!
#2620000
0!
#2625000
b101 #
1&
b0 %
1!
#2630000
0!
#2635000
b1 %
1!
#2640000
0!
#2645000
b10 %
1!
#2650000
0!
#2655000
1(
b0 $
b11 %
1!
#2660000
0!
#2665000
b100 %
1!
#2670000
0!
#2675000
b101 %
1!
#2680000
0!
#2685000
b110 %
1!
#2690000
0!
#2695000
0&
b111 %
1!
#2700000
0!
#2705000
b100 '
b110 #
1&
b0 %
1!
#2710000
0!
#2715000
b1 %
1!
#2720000
0!
#2725000
b10 %
1!
#2730000
0!
#2735000
0(
b1 $
b11 %
1!
#2740000
0!
#2745000
b100 %
1!
#2750000
0!
#2755000
b101 %
1!
#2760000
0!
#2765000
b110 %
1!
#2770000
0!
#2775000
0&
b111 %
1!
#2780000
0!
#2785000
b1000 '
b111 #
1&
b0 %
1!
#2790000
0!
#2795000
b11111111 $
b1 %
1!
#2800000
0!
#2805000
b10 %
1!
#2810000
0!
#2815000
b11 $
b11 %
1!
#2820000
0!
#2825000
0&
b100 %
1!
#2830000
0!
#2835000
b10 '
b1000 #
1&
b0 %
1!
#2840000
0!
#2845000
b1 %
0&
1!
#2850000
0!
#2855000
b0 '
b100 #
b0 %
1&
1!
#2860000
0!
#2865000
b101 $
b1 %
1!
#2870000
0!
#2875000
b10 %
1!
#2880000
0!
#2885000
b111100 $
b11 %
1!
#2890000
0!
#2895000
b100 %
1!
#2900000
0!
#2905000
b101 %
1!
#2910000
0!
#2915000
b110 %
1!
#2920000
0!
#2925000
0&
b111 %
1!
#2930000
0!
#2935000
b101 #
1&
b0 %
1!
#2940000
0!
#2945000
b1 %
1!
#2950000
0!
#2955000
b10 %
1!
#2960000
0!
#2965000
1(
b0 $
b11 %
1!
#2970000
0!
#2975000
b100 %
1!
#2980000
0!
#2985000
b101 %
1!
#2990000
0!
#2995000
b110 %
1!
#3000000
0!
#3005000
0&
b111 %
1!
#3010000
0!
#3015000
b100 '
b110 #
1&
b0 %
1!
#3020000
0!
#3025000
b1 %
1!
#3030000
0!
#3035000
b10 %
1!
#3040000
0!
#3045000
0(
b10 $
b11 %
1!
#3050000
0!
#3055000
b100 %
1!
#3060000
0!
#3065000
b101 %
1!
#3070000
0!
#3075000
b110 %
1!
#3080000
0!
#3085000
0&
b111 %
1!
#3090000
0!
#3095000
b1000 '
b111 #
1&
b0 %
1!
#3100000
0!
#3105000
1(
b0 $
b1 %
1!
#3110000
0!
#3115000
b10 %
1!
#3120000
0!
#3125000
0(
b10 $
b11 %
1!
#3130000
0!
#3135000
0&
b100 %
1!
#3140000
0!
#3145000
b10 '
b1000 #
1&
b0 %
1!
#3150000
0!
#3155000
b1 %
0&
1!
#3160000
0!
#3165000
b0 '
b100 #
b0 %
1&
1!
#3170000
0!
#3175000
b110 $
b1 %
1!
#3180000
0!
#3185000
b10 %
1!
#3190000
0!
#3195000
b1011010 $
b11 %
1!
#3200000
0!
#3205000
b100 %
1!
#3210000
0!
#3215000
b101 %
1!
#3220000
0!
#3225000
b110 %
1!
#3230000
0!
#3235000
0&
b111 %
1!
#3240000
0!
#3245000
b101 #
1&
b0 %
1!
#3250000
0!
#3255000
b1 %
1!
#3260000
0!
#3265000
b10 %
1!
#3270000
0!
#3275000
1(
b0 $
b11 %
1!
#3280000
0!
#3285000
b100 %
1!
#3290000
0!
#3295000
b101 %
1!
#3300000
0!
#3305000
b110 %
1!
#3310000
0!
#3315000
0&
b111 %
1!
#3320000
0!
#3325000
b100 '
b110 #
1&
b0 %
1!
#3330000
0!
#3335000
b1 %
1!
#3340000
0!
#3345000
b10 %
1!
#3350000
0!
#3355000
0(
b11 $
b11 %
1!
#3360000
0!
#3365000
b100 %
1!
#3370000
0!
#3375000
b101 %
1!
#3380000
0!
#3385000
b110 %
1!
#3390000
0!
#3395000
0&
b111 %
1!
#3400000
0!
#3405000
b1000 '
b111 #
1&
b0 %
1!
#3410000
0!
#3415000
b1 $
b1 %
1!
#3420000
0!
#3425000
b10 %
1!
#3430000
0!
#3435000
b11 %
1!
#3440000
0!
#3445000
0&
b100 %
1!
#3450000
0!
#3455000
b10 '
b1000 #
1&
b0 %
1!
#3460000
0!
#3465000
b1 %
0&
1!
#3470000
0!
#3475000
b0 '
b100 #
b0 %
1&
1!
#3480000
0!
#3485000
b111 $
b1 %
1!
#3490000
0!
#3495000
b10 %
1!
#3500000
0!
#3505000
b1111000 $
b11 %
1!
#3510000
0!
#3515000
b100 %
1!
#3520000
0!
#3525000
b101 %
1!
#3530000
0!
#3535000
b110 %
1!
#3540000
0!
#3545000
0&
b111 %
1!
#3550000
0!
#3555000
b101 #
1&
b0 %
1!
#3560000
0!
#3565000
b1 %
1!
#3570000
0!
#3575000
b10 %
1!
#3580000
0!
#3585000
1(
b0 $
b11 %
1!
#3590000
0!
#3595000
b100 %
1!
#3600000
0!
#3605000
b101 %
1!
#3610000
0!
